<?xml version="1.0" encoding="utf-8" ?><dwsync><file name="avast.jpg" server="qxu1194690288.my3w.com//htdocs/" local="3533597272" remote="3533598000" Dst="-1" /><file name="avg.jpg" server="qxu1194690288.my3w.com//htdocs/" local="3533597272" remote="3533598000" Dst="-1" /><file name="av.jpg" server="qxu1194690288.my3w.com//htdocs/" local="3533597272" remote="3533598000" Dst="-1" /><file name="ahnlab.jpg" server="qxu1194690288.my3w.com//htdocs/" local="3533597272" remote="3533598000" Dst="-1" /><file name="avira.jpg" server="qxu1194690288.my3w.com//htdocs/" local="3533597272" remote="3533598000" Dst="-1" /><file name="bitdefender.jpg" server="qxu1194690288.my3w.com//htdocs/" local="3533597272" remote="3533598000" Dst="-1" /><file name="baidu.jpg" server="qxu1194690288.my3w.com//htdocs/" local="3533597272" remote="3533598000" Dst="-1" /><file name="bullguard.jpg" server="qxu1194690288.my3w.com//htdocs/" local="3533597272" remote="3533598000" Dst="-1" /><file name="doctor web.jpg" server="qxu1194690288.my3w.com//htdocs/" local="3533597272" remote="3533598000" Dst="-1" /><file name="emsisoft.jpg" server="qxu1194690288.my3w.com//htdocs/" local="3533597272" remote="3533598000" Dst="-1" /><file name="escan.jpg" server="qxu1194690288.my3w.com//htdocs/" local="3533597272" remote="3533598000" Dst="-1" /><file name="f-secure.jpg" server="qxu1194690288.my3w.com//htdocs/" local="3533597272" remote="3533598000" Dst="-1" /><file name="fortinet.jpg" server="qxu1194690288.my3w.com//htdocs/" local="3533597272" remote="3533598000" Dst="-1" /><file name="eset.jpg" server="qxu1194690288.my3w.com//htdocs/" local="3533597272" remote="3533598000" Dst="-1" /><file name="frisk.jpg" server="qxu1194690288.my3w.com//htdocs/" local="3533597272" remote="3533598000" Dst="-1" /><file name="g data.jpg" server="qxu1194690288.my3w.com//htdocs/" local="3533597272" remote="3533598000" Dst="-1" /><file name="k7.jpg" server="qxu1194690288.my3w.com//htdocs/" local="3533597272" remote="3533598000" Dst="-1" /><file name="gecad software.jpg" server="qxu1194690288.my3w.com//htdocs/" local="3533597272" remote="3533598060" Dst="-1" /><file name="kaspersky.jpg" server="qxu1194690288.my3w.com//htdocs/" local="3533597272" remote="3533598060" Dst="-1" /><file name="kingsoft.jpg" server="qxu1194690288.my3w.com//htdocs/" local="3533597272" remote="3533598060" Dst="-1" /><file name="lavasoft.jpg" server="qxu1194690288.my3w.com//htdocs/" local="3533597272" remote="3533598060" Dst="-1" /><file name="mcafee.jpg" server="qxu1194690288.my3w.com//htdocs/" local="3533597272" remote="3533598060" Dst="-1" /><file name="microsoft.jpg" server="qxu1194690288.my3w.com//htdocs/" local="3533597272" remote="3533598060" Dst="-1" /><file name="norman.jpg" server="qxu1194690288.my3w.com//htdocs/" local="3533597272" remote="3533598060" Dst="-1" /><file name="pc tools.jpg" server="qxu1194690288.my3w.com//htdocs/" local="3533597272" remote="3533598060" Dst="-1" /><file name="panda.jpg" server="qxu1194690288.my3w.com//htdocs/" local="3533597272" remote="3533598060" Dst="-1" /><file name="qihoo - 360.jpg" server="qxu1194690288.my3w.com//htdocs/" local="3533597272" remote="3533598060" Dst="-1" /><file name="quick heal.jpg" server="qxu1194690288.my3w.com//htdocs/" local="3533597272" remote="3533598060" Dst="-1" /><file name="sophos.jpg" server="qxu1194690288.my3w.com//htdocs/" local="3533597272" remote="3533598060" Dst="-1" /><file name="symantec.jpg" server="qxu1194690288.my3w.com//htdocs/" local="3533597272" remote="3533598060" Dst="-1" /><file name="tencent.jpg" server="qxu1194690288.my3w.com//htdocs/" local="3533597272" remote="3533598060" Dst="-1" /><file name="threattrack vipre.jpg" server="qxu1194690288.my3w.com//htdocs/" local="3533597272" remote="3533598060" Dst="-1" /><file name="trend micro.jpg" server="qxu1194690288.my3w.com//htdocs/" local="3533597272" remote="3533598060" Dst="-1" /><file name="trustport.jpg" server="qxu1194690288.my3w.com//htdocs/" local="3533597272" remote="3533598060" Dst="-1" /><file name="virusblokada.jpg" server="qxu1194690288.my3w.com//htdocs/" local="3533597272" remote="3533598060" Dst="-1" /><file name="webroot.jpg" server="qxu1194690288.my3w.com//htdocs/" local="3533597272" remote="3533598060" Dst="-1" /></dwsync>